yarals/__init__.py
yarals/helpers.py
yarals/run_server.py
yarals/yarals.py
yarals/base/__init__.py
yarals/base/errors.py
yarals/base/protocol.py
yarals/base/server.py
yarals/data/modules.json
yara_language_server-0.0.4.dist-info/LICENSE
yara_language_server-0.0.4.dist-info/METADATA
yara_language_server-0.0.4.dist-info/WHEEL
yara_language_server-0.0.4.dist-info/entry_points.txt
yara_language_server-0.0.4.dist-info/top_level.txt
yara_language_server-0.0.4.dist-info/RECORD
