Metadata-Version: 2.1
Name: yara-language-server
Version: 0.0.4
Summary: 
